showprompt/__init__.py
showprompt/test_showprompt.py
showprompt-0.1.0.dist-info/LICENSE
showprompt-0.1.0.dist-info/METADATA
showprompt-0.1.0.dist-info/WHEEL
showprompt-0.1.0.dist-info/top_level.txt
showprompt-0.1.0.dist-info/RECORD
