Metadata-Version: 2.2
Name: showprompt
Version: 0.1.0
Summary: Inspect in-flight LLM prompts with 1 line of code
Author-email: showprompt <example@example.com>
License: MIT
Project-URL: Homepage, https://github.com/yourusername/showprompt
Project-URL: Issues, https://github.com/yourusername/showprompt/issues
Keywords: llm,prompt,ai,openai,debug
Classifier: Programming Language :: Python :: 3
Classifier: License :: OSI Approved :: MIT License
Classifier: Operating System :: OS Independent
Requires-Python: >=3.7
License-File: LICENSE
